hnt_jira/__init__.py
hnt_jira/constants.py
hnt_jira/hnt_jira.py
hnt_jira/attachment/jira_api.py
hnt_jira_library-0.0.1.dist-info/METADATA
hnt_jira_library-0.0.1.dist-info/WHEEL
hnt_jira_library-0.0.1.dist-info/top_level.txt
hnt_jira_library-0.0.1.dist-info/RECORD
